primenumber_ioanbeilic/__init__.py
primenumber_ioanbeilic-1.0.dist-info/LICENSE
primenumber_ioanbeilic-1.0.dist-info/METADATA
primenumber_ioanbeilic-1.0.dist-info/WHEEL
primenumber_ioanbeilic-1.0.dist-info/top_level.txt
primenumber_ioanbeilic-1.0.dist-info/RECORD
