Metadata-Version: 2.1
Name: primenumber-ioanbeilic
Version: 1.0
Summary: A tool ger prime number.
Home-page: UNKNOWN
Author: Iona beilic
Author-email: ioanbeilic@gmail.com
License: GNU GPLv3
Keywords: pyoperaciones mathematical operations
Platform: UNKNOWN
Classifier: Development Status :: 4 - Beta
Classifier: Intended Audience :: Developers
Classifier: Topic :: Utilities
Classifier: License :: OSI Approved :: GNU General Public License v3 (GPLv3)
Classifier: Programming Language :: Python :: 3
Classifier: Operating System :: OS Independent
License-File: LICENSE
